pynbt.py
PyNBT-3.1.0.dist-info/LICENCE
PyNBT-3.1.0.dist-info/METADATA
PyNBT-3.1.0.dist-info/WHEEL
PyNBT-3.1.0.dist-info/top_level.txt
PyNBT-3.1.0.dist-info/RECORD
