Metadata-Version: 2.1
Name: PyNBT
Version: 3.1.0
Summary: Tiny, liberally-licensed NBT library (Minecraft).
Home-page: https://github.com/TkTech/PyNBT
Author: Tyler Kennedy
Author-email: tk@tkte.ch
License: UNKNOWN
Keywords: minecraft,nbt
Platform: UNKNOWN
Classifier: Development Status :: 5 - Production/Stable
Classifier: Intended Audience :: Developers
Classifier: Operating System :: OS Independent
Classifier: License :: OSI Approved :: MIT License
Provides-Extra: test
